pycommonlog/__init__.py
pycommonlog/cache.py
pycommonlog/log_types.py
pycommonlog/logger.py
pycommonlog-0.2.1.dist-info/licenses/LICENSE
pycommonlog-0.2.1.dist-info/METADATA
pycommonlog-0.2.1.dist-info/WHEEL
pycommonlog-0.2.1.dist-info/top_level.txt
pycommonlog-0.2.1.dist-info/RECORD
