Metadata-Version: 2.4
Name: pycommonlog
Version: 0.2.1
Summary: Unified logging and alerting library for Python.
Home-page: https://github.com/alvianhanif/pycommonlog
Author: Alvian Rahman Hanif
Author-email: alvian.hanif@pasarpolis.com
License: MIT
Classifier: Programming Language :: Python :: 3
Classifier: License :: OSI Approved :: MIT License
Classifier: Operating System :: OS Independent
Requires-Python: >=3.8
License-File: LICENSE
Dynamic: author
Dynamic: author-email
Dynamic: classifier
Dynamic: description
Dynamic: description-content-type
Dynamic: home-page
Dynamic: license
Dynamic: license-file
Dynamic: requires-python
Dynamic: summary
